django_permission_engine/__init__.py
django_permission_engine/apps.py
django_permission_engine/helpers.py
django_permission_engine/models.py
django_permission_engine/permission_management.py
django_permission_engine/permissions.py
django_permission_engine/registry.py
django_permission_engine/urls.py
django_permission_engine/views.py
django_permission_engine/management/__init__.py
django_permission_engine/management/commands/__init__.py
django_permission_engine/management/commands/upr_list.py
django_permission_engine/management/commands/upr_sync.py
django_permission_engine/management/commands/upr_validate.py
django_permission_engine/migrations/0001_initial.py
django_permission_engine/migrations/__init__.py
django_permission_engine-0.1.3.dist-info/licenses/LICENSE
django_permission_engine-0.1.3.dist-info/METADATA
django_permission_engine-0.1.3.dist-info/WHEEL
django_permission_engine-0.1.3.dist-info/top_level.txt
django_permission_engine-0.1.3.dist-info/RECORD
