Metadata-Version: 2.4
Name: django-permission-engine
Version: 0.1.3
Summary: Unified Permission Registry (UPR) for Django & DRF
Home-page: https://github.com/sarthaksnh5/django_permission_engine
Author: Sarthak
Author-email: sarthaksnh5@gmail.com
License: MIT
Project-URL: Documentation, https://django-permission-engine.readthedocs.io/
Project-URL: Source, https://github.com/sarthaksnh5/django_permission_engine
Project-URL: Tracker, https://github.com/sarthaksnh5/django_permission_engine/issues
Keywords: django permissions drf rest-framework
Classifier: Development Status :: 3 - Alpha
Classifier: Intended Audience :: Developers
Classifier: License :: OSI Approved :: MIT License
Classifier: Programming Language :: Python :: 3
Classifier: Programming Language :: Python :: 3.8
Classifier: Programming Language :: Python :: 3.9
Classifier: Programming Language :: Python :: 3.10
Classifier: Programming Language :: Python :: 3.11
Classifier: Framework :: Django
Classifier: Framework :: Django :: 3.2
Classifier: Framework :: Django :: 4.0
Classifier: Framework :: Django :: 4.1
Classifier: Framework :: Django :: 4.2
Requires-Python: >=3.8
License-File: LICENSE
Requires-Dist: Django>=3.2
Requires-Dist: djangorestframework>=3.12
Dynamic: author
Dynamic: author-email
Dynamic: classifier
Dynamic: description
Dynamic: description-content-type
Dynamic: home-page
Dynamic: keywords
Dynamic: license
Dynamic: license-file
Dynamic: project-url
Dynamic: requires-dist
Dynamic: requires-python
Dynamic: summary
